ctapipe_io_lst/__init__.py
ctapipe_io_lst/_version.py
ctapipe_io_lst/anyarray_dtypes.py
ctapipe_io_lst/calibration.py
ctapipe_io_lst/compat.py
ctapipe_io_lst/constants.py
ctapipe_io_lst/containers.py
ctapipe_io_lst/evb_preprocessing.py
ctapipe_io_lst/event_time.py
ctapipe_io_lst/ground_frame.py
ctapipe_io_lst/multifiles.py
ctapipe_io_lst/pixels.py
ctapipe_io_lst/pointing.py
ctapipe_io_lst/version.py
ctapipe_io_lst/resources/LSTCam.camgeom.fits.gz
ctapipe_io_lst/resources/no_corrections_pulse_LST.dat
ctapipe_io_lst/resources/oversampled_pulse_LST_8dynode_pix6_20200204.dat
ctapipe_io_lst/tests/__init__.py
ctapipe_io_lst/tests/test_anyarray_dtypes.py
ctapipe_io_lst/tests/test_calib.py
ctapipe_io_lst/tests/test_cta_r1.py
ctapipe_io_lst/tests/test_evb_preprocessing.py
ctapipe_io_lst/tests/test_event_time.py
ctapipe_io_lst/tests/test_lsteventsource.py
ctapipe_io_lst/tests/test_multifile.py
ctapipe_io_lst/tests/test_pixels.py
ctapipe_io_lst/tests/test_pointing.py
ctapipe_io_lst/tests/test_stage1.py
ctapipe_io_lst/tests/test_version.py
ctapipe_io_lst/tests/resources/first_caps.hdf5
ctapipe_io_lst-0.27.2.dist-info/licenses/LICENSE
ctapipe_io_lst-0.27.2.dist-info/METADATA
ctapipe_io_lst-0.27.2.dist-info/WHEEL
ctapipe_io_lst-0.27.2.dist-info/entry_points.txt
ctapipe_io_lst-0.27.2.dist-info/top_level.txt
ctapipe_io_lst-0.27.2.dist-info/RECORD
