Metadata-Version: 2.4
Name: ctapipe_io_lst
Version: 0.27.2
Summary: ctapipe plugin for reading LST prototype files
Author: CTA LST Project
Author-email: maximilian.linhoff@tu-dortmund.de
License: BSD 3-clause
Project-URL: Bug Tracker, https://github.com/cta-observatory/ctapipe_io_lst/issues
Project-URL: Source Code, https://github.com/cta-observatory/ctapipe_io_lst
Classifier: Development Status :: 4 - Beta
Classifier: License :: OSI Approved :: MIT License
Classifier: Intended Audience :: Science/Research
Classifier: Topic :: Scientific/Engineering :: Astronomy
Classifier: Topic :: Scientific/Engineering :: Physics
Classifier: Programming Language :: Python :: 3 :: Only
Classifier: Programming Language :: Python :: 3.10
Classifier: Programming Language :: Python :: 3.11
Classifier: Programming Language :: Python :: 3.12
Classifier: Programming Language :: Python :: 3.13
Requires-Python: >=3.10
License-File: LICENSE
Requires-Dist: astropy<8.0.0a0,>=5.2
Requires-Dist: ctapipe<0.27.0a0,>=0.23.2
Requires-Dist: protozfits~=2.6
Requires-Dist: numpy>=1.20
Requires-Dist: scipy
Provides-Extra: tests
Requires-Dist: pytest; extra == "tests"
Provides-Extra: dev
Requires-Dist: setuptools_scm[toml]; extra == "dev"
Provides-Extra: all
Requires-Dist: pytest; extra == "all"
Requires-Dist: setuptools_scm[toml]; extra == "all"
Dynamic: license-file
